geomagnetism/FORTRAN_1900_1995.txt
geomagnetism/FORTRAN_2000_2020.txt
geomagnetism/IGRF13.COF
geomagnetism/IGRF13coeffs.txt
geomagnetism/WMM2020testvalues.xlsx
geomagnetism/WMM_2015.COF
geomagnetism/WMM_2020.COF
geomagnetism/WMM_hight_precision.txt
geomagnetism/__init__.py
geomagnetism/geomagnetism.py
geomagnetism/read_geo_data.py
geomagnetism-0.1.0.dist-info/LICENSE
geomagnetism-0.1.0.dist-info/METADATA
geomagnetism-0.1.0.dist-info/WHEEL
geomagnetism-0.1.0.dist-info/top_level.txt
geomagnetism-0.1.0.dist-info/RECORD
