Metadata-Version: 2.1
Name: geomagnetism
Version: 0.1.0
Summary: toolbox for geomagnetism computation
Home-page: https://github.com/Bertin-fap/geomagnetism-exemples
Author: ArrayStream(François Bertin)
Author-email: francois.bertin7@wanadoo.fr
License: MIT
Keywords: Geomagnetism,magnetism,data processing
Platform: UNKNOWN
Classifier: Development Status :: 3 - Alpha
Classifier: License :: OSI Approved :: MIT License
Classifier: Programming Language :: Python :: 3.6
Classifier: Topic :: Scientific/Engineering :: Physics
Classifier: Operating System :: OS Independent
Classifier: Intended Audience :: Science/Research
Requires-Dist: pandas
Requires-Dist: numpy
Requires-Dist: scipy
Requires-Dist: xarray
